download_arxiv.py
download_arxiv-0.1.7.dist-info/entry_points.txt
download_arxiv-0.1.7.dist-info/WHEEL
download_arxiv-0.1.7.dist-info/METADATA
download_arxiv-0.1.7.dist-info/RECORD
